reactor/__init__.py
reactor/app.py
reactor/asgi.py
reactor/auto_broadcast.py
reactor/channels.py
reactor/component.py
reactor/json.py
reactor/log.py
reactor/middleware.py
reactor/settings.py
reactor/static/reactor/.gitignore
reactor/static/reactor/morphdom.min.js
reactor/static/reactor/reactor.coffee
reactor/static/reactor/reactor.css
reactor/static/reactor/reactor.js
reactor/static/reactor/turbolinks.min.js
reactor/templates/reactor_header.html
reactor/templatetags/__init__.py
reactor/templatetags/reactor.py
reactor/tests.py
reactor/utils.py
django_reactor-2.2.1b0.dist-info/WHEEL
django_reactor-2.2.1b0.dist-info/METADATA
django_reactor-2.2.1b0.dist-info/RECORD
