Metadata-Version: 2.1
Name: django-reactor
Version: 2.2.1b0
Summary: Brings LiveView from Phoenix framework into Django
Home-page: https://github.com/edelvalle/reactor
License: MIT
Keywords: django,python,javascript,fullstack,liveview
Author: Eddy Ernesto del Valle Pino
Author-email: eddy@edelvalle.me
Requires-Python: >=3.6,<4
Classifier: License :: OSI Approved :: MIT License
Classifier: Programming Language :: Python :: 3
Classifier: Programming Language :: Python :: 3.6
Classifier: Programming Language :: Python :: 3.7
Classifier: Programming Language :: Python :: 3.8
Classifier: Programming Language :: Python :: 3.9
Requires-Dist: channels (>=2.2.0,<2.5)
Requires-Dist: orjson (>=3,<4)
Requires-Dist: splinter[django] (>=0.14.0,<0.15.0)
Project-URL: Repository, https://github.com/edelvalle/reactor
